<annotation>
	<folder>Kudi</folder>
	<filename>image_309.png</filename>
	<path>C:\Users\Kudi Okerulu\Desktop\Thesis\Data\Kudi\image_309.png</path>
	<source>
		<database>Unknown</database>
	</source>
	<size>
		<width>220</width>
		<height>220</height>
		<depth>1</depth>
	</size>
	<segmented>0</segmented>
	<object>
		<name>Living Cell</name>
		<pose>Unspecified</pose>
		<truncated>0</truncated>
		<difficult>0</difficult>
		<bndbox>
			<xmin>57</xmin>
			<ymin>89</ymin>
			<xmax>80</xmax>
			<ymax>118</ymax>
		</bndbox>
	</object>
	<object>
		<name>Living Cell</name>
		<pose>Unspecified</pose>
		<truncated>0</truncated>
		<difficult>0</difficult>
		<bndbox>
			<xmin>49</xmin>
			<ymin>183</ymin>
			<xmax>74</xmax>
			<ymax>210</ymax>
		</bndbox>
	</object>
	<object>
		<name>Living Cell</name>
		<pose>Unspecified</pose>
		<truncated>0</truncated>
		<difficult>0</difficult>
		<bndbox>
			<xmin>110</xmin>
			<ymin>164</ymin>
			<xmax>126</xmax>
			<ymax>187</ymax>
		</bndbox>
	</object>
	<object>
		<name>Living Cell</name>
		<pose>Unspecified</pose>
		<truncated>0</truncated>
		<difficult>0</difficult>
		<bndbox>
			<xmin>143</xmin>
			<ymin>148</ymin>
			<xmax>162</xmax>
			<ymax>166</ymax>
		</bndbox>
	</object>
	<object>
		<name>Living Cell</name>
		<pose>Unspecified</pose>
		<truncated>0</truncated>
		<difficult>0</difficult>
		<bndbox>
			<xmin>126</xmin>
			<ymin>161</ymin>
			<xmax>157</xmax>
			<ymax>191</ymax>
		</bndbox>
	</object>
	<object>
		<name>Living Cell</name>
		<pose>Unspecified</pose>
		<truncated>0</truncated>
		<difficult>0</difficult>
		<bndbox>
			<xmin>123</xmin>
			<ymin>184</ymin>
			<xmax>144</xmax>
			<ymax>205</ymax>
		</bndbox>
	</object>
</annotation>
