<annotation>
	<folder>Kudi</folder>
	<filename>ncell (164).png</filename>
	<path>C:\Users\Kudi Okerulu\Desktop\Thesis\Data\Kudi\ncell (164).png</path>
	<source>
		<database>Unknown</database>
	</source>
	<size>
		<width>225</width>
		<height>219</height>
		<depth>1</depth>
	</size>
	<segmented>0</segmented>
	<object>
		<name>Living Cell</name>
		<pose>Unspecified</pose>
		<truncated>0</truncated>
		<difficult>0</difficult>
		<bndbox>
			<xmin>4</xmin>
			<ymin>61</ymin>
			<xmax>18</xmax>
			<ymax>77</ymax>
		</bndbox>
	</object>
	<object>
		<name>Living Cell</name>
		<pose>Unspecified</pose>
		<truncated>0</truncated>
		<difficult>0</difficult>
		<bndbox>
			<xmin>14</xmin>
			<ymin>94</ymin>
			<xmax>31</xmax>
			<ymax>112</ymax>
		</bndbox>
	</object>
	<object>
		<name>Living Cell</name>
		<pose>Unspecified</pose>
		<truncated>0</truncated>
		<difficult>0</difficult>
		<bndbox>
			<xmin>137</xmin>
			<ymin>171</ymin>
			<xmax>154</xmax>
			<ymax>188</ymax>
		</bndbox>
	</object>
	<object>
		<name>Dead Cell</name>
		<pose>Unspecified</pose>
		<truncated>0</truncated>
		<difficult>0</difficult>
		<bndbox>
			<xmin>56</xmin>
			<ymin>149</ymin>
			<xmax>75</xmax>
			<ymax>167</ymax>
		</bndbox>
	</object>
	<object>
		<name>Dead Cell</name>
		<pose>Unspecified</pose>
		<truncated>0</truncated>
		<difficult>0</difficult>
		<bndbox>
			<xmin>126</xmin>
			<ymin>100</ymin>
			<xmax>144</xmax>
			<ymax>119</ymax>
		</bndbox>
	</object>
	<object>
		<name>Dead Cell</name>
		<pose>Unspecified</pose>
		<truncated>0</truncated>
		<difficult>0</difficult>
		<bndbox>
			<xmin>173</xmin>
			<ymin>94</ymin>
			<xmax>193</xmax>
			<ymax>114</ymax>
		</bndbox>
	</object>
</annotation>
